opencode_ai/__init__.py
opencode_ai/_base_client.py
opencode_ai/_client.py
opencode_ai/_compat.py
opencode_ai/_constants.py
opencode_ai/_exceptions.py
opencode_ai/_files.py
opencode_ai/_models.py
opencode_ai/_qs.py
opencode_ai/_resource.py
opencode_ai/_response.py
opencode_ai/_streaming.py
opencode_ai/_types.py
opencode_ai/_version.py
opencode_ai/py.typed
opencode_ai/_utils/__init__.py
opencode_ai/_utils/_logs.py
opencode_ai/_utils/_proxy.py
opencode_ai/_utils/_reflection.py
opencode_ai/_utils/_resources_proxy.py
opencode_ai/_utils/_streams.py
opencode_ai/_utils/_sync.py
opencode_ai/_utils/_transform.py
opencode_ai/_utils/_typing.py
opencode_ai/_utils/_utils.py
opencode_ai/lib/.keep
opencode_ai/resources/__init__.py
opencode_ai/resources/app.py
opencode_ai/resources/config.py
opencode_ai/resources/event.py
opencode_ai/resources/file.py
opencode_ai/resources/find.py
opencode_ai/resources/session.py
opencode_ai/resources/tui.py
opencode_ai/types/__init__.py
opencode_ai/types/app.py
opencode_ai/types/app_init_response.py
opencode_ai/types/app_log_params.py
opencode_ai/types/app_log_response.py
opencode_ai/types/app_modes_response.py
opencode_ai/types/app_providers_response.py
opencode_ai/types/assistant_message.py
opencode_ai/types/config.py
opencode_ai/types/event_list_response.py
opencode_ai/types/file.py
opencode_ai/types/file_part.py
opencode_ai/types/file_part_input_param.py
opencode_ai/types/file_part_source.py
opencode_ai/types/file_part_source_param.py
opencode_ai/types/file_part_source_text.py
opencode_ai/types/file_part_source_text_param.py
opencode_ai/types/file_read_params.py
opencode_ai/types/file_read_response.py
opencode_ai/types/file_source.py
opencode_ai/types/file_source_param.py
opencode_ai/types/file_status_response.py
opencode_ai/types/find_files_params.py
opencode_ai/types/find_files_response.py
opencode_ai/types/find_symbols_params.py
opencode_ai/types/find_symbols_response.py
opencode_ai/types/find_text_params.py
opencode_ai-0.1.0a36.dist-info/METADATA
opencode_ai-0.1.0a36.dist-info/WHEEL
opencode_ai-0.1.0a36.dist-info/licenses/LICENSE
opencode_ai-0.1.0a36.dist-info/RECORD
